jupyter-config/jupyter_server_config.d/jupyter_cadquery.json
jupyter_cadquery/__init__.py
jupyter_cadquery/_version.py
jupyter_cadquery/app.py
jupyter_cadquery/comms.py
jupyter_cadquery/config.py
jupyter_cadquery/logo.py
jupyter_cadquery/replay.py
jupyter_cadquery/show.py
jupyter_cadquery/tools.py
jupyter_cadquery-4.0.2.data/data/etc/jupyter/jupyter_server_config.d/jupyter_cadquery.json
jupyter_cadquery-4.0.2.dist-info/METADATA
jupyter_cadquery-4.0.2.dist-info/WHEEL
jupyter_cadquery-4.0.2.dist-info/licenses/LICENSE
jupyter_cadquery-4.0.2.dist-info/RECORD
