Metadata-Version: 2.4
Name: jupyter_cadquery
Version: 4.0.2
Summary: An extension to render cadquery objects in JupyterLab via pythreejs
Author-email: Bernhard Walter <b_walter@arcor.de>
License: 
License-File: LICENSE
Keywords: CAD,cadquery,ipython,jupyter,widgets
Classifier: Development Status :: 5 - Production/Stable
Classifier: Framework :: IPython
Classifier: Intended Audience :: Developers
Classifier: Intended Audience :: Science/Research
Classifier: Programming Language :: Python :: 3
Classifier: Programming Language :: Python :: 3.8
Classifier: Programming Language :: Python :: 3.9
Classifier: Programming Language :: Python :: 3.10
Classifier: Programming Language :: Python :: 3.11
Classifier: Programming Language :: Python :: 3.12
Classifier: Topic :: Multimedia :: Graphics
Requires-Python: >=3.8
Requires-Dist: cachetools~=5.5.0
Requires-Dist: cad-viewer-widget~=3.0.2
Requires-Dist: jupyterlab<5,>=4.3.6
Requires-Dist: ocp-vscode~=2.7.0
Requires-Dist: orjson~=3.10.16
Requires-Dist: webcolors~=24.8.0
Provides-Extra: dev
Requires-Dist: black; extra == 'dev'
Requires-Dist: bumpversion; extra == 'dev'
Requires-Dist: cookiecutter; extra == 'dev'
Requires-Dist: jupyter-packaging; extra == 'dev'
Requires-Dist: pylint; extra == 'dev'
Requires-Dist: pyyaml; extra == 'dev'
Requires-Dist: twine; extra == 'dev'
